f_cli/__init__.py
f_cli/cli.py
f_cli-0.0.0.dist-info/LICENSE
f_cli-0.0.0.dist-info/METADATA
f_cli-0.0.0.dist-info/WHEEL
f_cli-0.0.0.dist-info/entry_points.txt
f_cli-0.0.0.dist-info/top_level.txt
f_cli-0.0.0.dist-info/RECORD
